Metadata-Version: 2.1
Name: paddle-fl-gpu
Version: 1.2.0
Summary: Privacy-Preserving Deep Learning Package Based on PaddlePaddle.
Home-page: https://github.com/PaddlePaddle/PaddleFL
Author: PaddlePaddle Author
Author-email: paddle-dev@baidu.com
License: Apache 2.0
Keywords: paddle_fl paddlepaddle multi-task transfer distributed-training multiparty-computation privacy-preserving
Platform: UNKNOWN
Classifier: Development Status :: 4 - Beta
Classifier: Intended Audience :: Developers
Classifier: Intended Audience :: Education
Classifier: Intended Audience :: Science/Research
Classifier: License :: OSI Approved :: Apache Software License
Classifier: Programming Language :: Python :: 2.7
Classifier: Programming Language :: Python :: 3
Classifier: Programming Language :: Python :: 3.4
Classifier: Programming Language :: Python :: 3.5
Classifier: Programming Language :: Python :: 3.6
Classifier: Topic :: Scientific/Engineering
Classifier: Topic :: Scientific/Engineering :: Mathematics
Classifier: Topic :: Scientific/Engineering :: Artificial Intelligence
Classifier: Topic :: Software Development
Classifier: Topic :: Software Development :: Libraries
Classifier: Topic :: Software Development :: Libraries :: Python Modules
Requires-Dist: six (>=1.10.0)
Requires-Dist: protobuf (>=3.1.0)
Requires-Dist: paddle-serving-client (==0.4.0)
Requires-Dist: paddlepaddle-gpu (>=1.8.5)
Requires-Dist: numpy
Requires-Dist: unittest2
